{"type": "FeatureCollection", "id": "https://pleiades.stoa.org/places/874771", "name": "874771", "features": [{"type": "Feature", "id": "http://data.archaeology.link/data/cigs/RUS", "name": "Toprakkale", "dateprops": [], "properties": {"http://purl.org/dc/elements/1.1/created": ["2021"], "http://purl.org/dc/elements/1.1/creator": ["http://data.archaeology.link/data/spphaefen/arthur_de_graauw"], "http://www.ancientports.com/ont#accuracy": ["3"], "http://www.opengis.net/ont/geosparql#hasGeometry": ["http://data.archaeology.link/data/cigs/RUS_geom"], "http://www.w3.org/1999/02/22-rdf-syntax-ns#type": ["http://www.ancientports.com/ont#CuneiformSite"], "http://www.w3.org/2000/01/rdf-schema#label": ["", "Toprakkale"], "http://www.wikidata.org/prop/direct/P1584": ["https://pleiades.stoa.org/places/874771"]}, "geometry": {"type": "Point", "coordinates": [43.4064, 38.5102]}}]}