{"type": "FeatureCollection", "id": "https://www.geonames.org/323694", "name": "323694", "features": [{"type": "Feature", "id": "http://data.archaeology.link/data/cigs/ARA", "name": "Aras", "dateprops": [], "properties": {"http://purl.org/dc/elements/1.1/created": ["2021"], "http://purl.org/dc/elements/1.1/creator": ["http://data.archaeology.link/data/spphaefen/arthur_de_graauw"], "http://www.ancientports.com/ont#accuracy": ["1"], "http://www.opengis.net/ont/geosparql#hasGeometry": ["http://data.archaeology.link/data/cigs/ARA_geom"], "http://www.w3.org/1999/02/22-rdf-syntax-ns#type": ["http://www.ancientports.com/ont#CuneiformSite"], "http://www.w3.org/2000/01/rdf-schema#label": ["", "Aras"], "http://www.wikidata.org/prop/direct/P1566": ["https://www.geonames.org/323694"]}, "geometry": {"type": "Point", "coordinates": [42.3081, 39.9893]}}]}