{"type": "FeatureCollection", "id": "https://pleiades.stoa.org/places/874396", "name": "874396", "features": [{"type": "Feature", "id": "http://data.archaeology.link/data/cigs/BTM", "name": "Bas\u1e6d\u0101m", "dateprops": [], "properties": {"http://purl.org/dc/elements/1.1/created": ["2021"], "http://purl.org/dc/elements/1.1/creator": ["http://data.archaeology.link/data/spphaefen/arthur_de_graauw"], "http://www.ancientports.com/ont#accuracy": ["2"], "http://www.opengis.net/ont/geosparql#hasGeometry": ["http://data.archaeology.link/data/cigs/BTM_geom"], "http://www.w3.org/1999/02/22-rdf-syntax-ns#type": ["http://www.ancientports.com/ont#CuneiformSite"], "http://www.w3.org/2000/01/rdf-schema#label": ["", "Bas\u1e6d\u0101m"], "http://www.w3.org/2002/07/owl#sameAs": ["http://entitydata.org/entity/Q605408"], "http://www.wikidata.org/prop/direct/P1584": ["https://pleiades.stoa.org/places/874396"]}, "geometry": {"type": "Point", "coordinates": [44.9473, 38.8859]}}]}