{"type": "FeatureCollection", "id": "http://entitydata.org/entity/Q55887438", "name": "Q55887438", "features": [{"type": "Feature", "id": "http://data.archaeology.link/data/cigs/KBL", "name": "Chaman-i \u1e24az\u0324\u016br\u012b", "dateprops": [], "properties": {"http://purl.org/dc/elements/1.1/created": ["2021"], "http://purl.org/dc/elements/1.1/creator": ["http://data.archaeology.link/data/spphaefen/arthur_de_graauw"], "http://www.ancientports.com/ont#accuracy": ["2"], "http://www.opengis.net/ont/geosparql#hasGeometry": ["http://data.archaeology.link/data/cigs/KBL_geom"], "http://www.w3.org/1999/02/22-rdf-syntax-ns#type": ["http://www.ancientports.com/ont#CuneiformSite"], "http://www.w3.org/2000/01/rdf-schema#label": ["", "Chaman-i \u1e24az\u0324\u016br\u012b"], "http://www.w3.org/2002/07/owl#sameAs": ["http://entitydata.org/entity/Q55887438"], "http://www.wikidata.org/prop/direct/P1566": ["https://www.geonames.org/9166131"]}, "geometry": {"type": "Point", "coordinates": [69.1954, 34.5153]}}]}