{"type": "FeatureCollection", "id": "https://pleiades.stoa.org/places/903002", "name": "903002", "features": [{"type": "Feature", "id": "http://data.archaeology.link/data/cigs/BIS", "name": "B\u012bsut\u016bn", "dateprops": [], "properties": {"http://purl.org/dc/elements/1.1/created": ["2021"], "http://purl.org/dc/terms/partOf": ["http://data.archaeology.link/data/cigs/bib_rattenborg_rune_2021_7330077"], "http://www.ancientports.com/ont#accuracy": ["3"], "http://www.opengis.net/ont/geosparql#hasGeometry": ["http://data.archaeology.link/data/cigs/BIS_geom"], "http://www.w3.org/1999/02/22-rdf-syntax-ns#type": ["http://www.ancientports.com/ont#CuneiformSite"], "http://www.w3.org/2000/01/rdf-schema#label": ["", "B\u012bsut\u016bn"], "http://www.wikidata.org/prop/direct/P1584": ["https://pleiades.stoa.org/places/903002"]}, "geometry": {"type": "Point", "coordinates": [47.4318, 34.3881]}}]}