{"type": "FeatureCollection", "id": "https://www.geonames.org/122847", "name": "122847", "features": [{"type": "Feature", "id": "http://data.archaeology.link/data/cigs/NJF", "name": "Najaf\u0101b\u0101d", "dateprops": [], "properties": {"http://purl.org/dc/elements/1.1/created": ["2021"], "http://www.ancientports.com/ont#accuracy": ["3"], "http://www.opengis.net/ont/geosparql#hasGeometry": ["http://data.archaeology.link/data/cigs/NJF_geom"], "http://www.w3.org/1999/02/22-rdf-syntax-ns#type": ["http://www.ancientports.com/ont#CuneiformSite"], "http://www.w3.org/2000/01/rdf-schema#label": ["", "Najaf\u0101b\u0101d"], "http://www.wikidata.org/prop/direct/P1566": ["https://www.geonames.org/122847"]}, "geometry": {"type": "Point", "coordinates": [47.9761, 34.6527]}}]}