{"type": "FeatureCollection", "id": "https://pleiades.stoa.org/places/874383", "name": "874383", "features": [{"type": "Feature", "id": "http://data.archaeology.link/data/cigs/PLU", "name": "Palu", "dateprops": [], "properties": {"http://purl.org/dc/elements/1.1/created": ["2021"], "http://purl.org/dc/elements/1.1/creator": ["http://data.archaeology.link/data/spphaefen/arthur_de_graauw"], "http://www.ancientports.com/ont#accuracy": ["2"], "http://www.opengis.net/ont/geosparql#hasGeometry": ["http://data.archaeology.link/data/cigs/PLU_geom"], "http://www.w3.org/1999/02/22-rdf-syntax-ns#type": ["http://www.ancientports.com/ont#CuneiformSite"], "http://www.w3.org/2000/01/rdf-schema#label": ["", "Palu"], "http://www.wikidata.org/prop/direct/P1584": ["https://pleiades.stoa.org/places/874383"]}, "geometry": {"type": "Point", "coordinates": [39.9535, 38.7023]}}]}