{"type": "FeatureCollection", "id": "https://www.geonames.org/6860535", "name": "6860535", "features": [{"type": "Feature", "id": "http://data.archaeology.link/data/cigs/YAR", "name": "Tall Y\u0101rah", "dateprops": [], "properties": {"http://purl.org/dc/elements/1.1/created": ["2021"], "http://purl.org/dc/elements/1.1/creator": ["http://data.archaeology.link/data/spphaefen/arthur_de_graauw"], "http://www.ancientports.com/ont#accuracy": ["3"], "http://www.opengis.net/ont/geosparql#hasGeometry": ["http://data.archaeology.link/data/cigs/YAR_geom"], "http://www.w3.org/1999/02/22-rdf-syntax-ns#type": ["http://www.ancientports.com/ont#CuneiformSite"], "http://www.w3.org/2000/01/rdf-schema#label": ["\u062a\u0644 \u064a\u0627\u0631\u0629", "Tall Y\u0101rah"], "http://www.wikidata.org/prop/direct/P1566": ["https://www.geonames.org/6860535"]}, "geometry": {"type": "Point", "coordinates": [43.2532, 36.4466]}}]}