{"type": "FeatureCollection", "id": "http://entitydata.org/entity/Q3398568", "name": "Q3398568", "features": [{"type": "Feature", "id": "http://data.archaeology.link/data/cigs/KZL", "name": "Tall Kazal", "dateprops": [], "properties": {"http://purl.org/dc/elements/1.1/created": ["2021"], "http://purl.org/dc/terms/partOf": ["http://data.archaeology.link/data/cigs/bib_rattenborg_rune_2021_7330077"], "http://www.ancientports.com/ont#accuracy": ["3"], "http://www.opengis.net/ont/geosparql#hasGeometry": ["http://data.archaeology.link/data/cigs/KZL_geom"], "http://www.w3.org/1999/02/22-rdf-syntax-ns#type": ["http://www.ancientports.com/ont#CuneiformSite"], "http://www.w3.org/2000/01/rdf-schema#label": ["\u062a\u0644 \u0643\u0632\u0644", "Tall Kazal"], "http://www.w3.org/2002/07/owl#sameAs": ["http://entitydata.org/entity/Q3398568"], "http://www.wikidata.org/prop/direct/P1566": ["https://www.geonames.org/163525"]}, "geometry": {"type": "Point", "coordinates": [35.9862, 34.7085]}}]}