{"type": "FeatureCollection", "id": "https://www.geonames.org/163577", "name": "163577", "features": [{"type": "Feature", "id": "http://data.archaeology.link/data/cigs/QHD", "name": "Tall al-H\u0101d\u012b", "dateprops": [], "properties": {"http://purl.org/dc/elements/1.1/created": ["2021"], "http://purl.org/dc/elements/1.1/creator": ["http://data.archaeology.link/data/spphaefen/arthur_de_graauw"], "http://www.ancientports.com/ont#accuracy": ["3"], "http://www.opengis.net/ont/geosparql#hasGeometry": ["http://data.archaeology.link/data/cigs/QHD_geom"], "http://www.w3.org/1999/02/22-rdf-syntax-ns#type": ["http://www.ancientports.com/ont#CuneiformSite"], "http://www.w3.org/2000/01/rdf-schema#label": ["\u062a\u0644 \u0627\u0644\u0647\u0627\u062f\u064a", "Tall al-H\u0101d\u012b"], "http://www.wikidata.org/prop/direct/P1566": ["https://www.geonames.org/163577"]}, "geometry": {"type": "Point", "coordinates": [41.865, 36.8707]}}]}