{"type": "FeatureCollection", "id": "https://pleiades.stoa.org/places/678418", "name": "678418", "features": [{"type": "Feature", "id": "http://data.archaeology.link/data/cigs/THA", "name": "Ta\u2018nak", "dateprops": [], "properties": {"http://purl.org/dc/elements/1.1/created": ["2021"], "http://purl.org/dc/terms/partOf": ["http://data.archaeology.link/data/cigs/bib_rattenborg_rune_2021_7330077"], "http://www.ancientports.com/ont#accuracy": ["3"], "http://www.ancientports.com/ont#cdli_provenience_id": ["435"], "http://www.opengis.net/ont/geosparql#hasGeometry": ["http://data.archaeology.link/data/cigs/THA_geom"], "http://www.w3.org/1999/02/22-rdf-syntax-ns#type": ["http://www.ancientports.com/ont#CuneiformSite"], "http://www.w3.org/2000/01/rdf-schema#label": ["Ta\u2018nak", "\u05ea\u05e2\u05e0\u05db"], "http://www.wikidata.org/prop/direct/P1566": ["https://www.geonames.org/281604"], "http://www.wikidata.org/prop/direct/P1584": ["https://pleiades.stoa.org/places/678418"]}, "geometry": {"type": "Point", "coordinates": [35.2195, 32.5216]}}]}