{"type": "FeatureCollection", "id": "http://entitydata.org/entity/Q1986456", "name": "Q1986456", "features": [{"type": "Feature", "id": "http://data.archaeology.link/data/cigs/SWE", "name": "Tall Suwaiyhat", "dateprops": [], "properties": {"http://purl.org/dc/elements/1.1/created": ["2021"], "http://www.ancientports.com/ont#accuracy": ["3"], "http://www.opengis.net/ont/geosparql#hasGeometry": ["http://data.archaeology.link/data/cigs/SWE_geom"], "http://www.w3.org/1999/02/22-rdf-syntax-ns#type": ["http://www.ancientports.com/ont#CuneiformSite"], "http://www.w3.org/2000/01/rdf-schema#label": ["Unknown", "Tall Suwaiyhat"], "http://www.w3.org/2002/07/owl#sameAs": ["http://entitydata.org/entity/Q1986456"]}, "geometry": {"type": "Point", "coordinates": [38.2538, 36.2734]}}]}