{"type": "FeatureCollection", "id": "http://entitydata.org/entity/Q1329616", "name": "Q1329616", "features": [{"type": "Feature", "id": "http://data.archaeology.link/data/cigs/TTU", "name": "Dicle T\u00fcneli", "dateprops": [], "properties": {"http://purl.org/dc/elements/1.1/created": ["2021"], "http://purl.org/dc/terms/partOf": ["http://data.archaeology.link/data/cigs/bib_rattenborg_rune_2021_7330077"], "http://www.ancientports.com/ont#accuracy": ["2"], "http://www.opengis.net/ont/geosparql#hasGeometry": ["http://data.archaeology.link/data/cigs/TTU_geom"], "http://www.w3.org/1999/02/22-rdf-syntax-ns#type": ["http://www.ancientports.com/ont#CuneiformSite"], "http://www.w3.org/2000/01/rdf-schema#label": ["", "Dicle T\u00fcneli"], "http://www.w3.org/2002/07/owl#sameAs": ["http://entitydata.org/entity/Q1329616"], "http://www.wikidata.org/prop/direct/P1566": ["https://www.geonames.org/6611419"]}, "geometry": {"type": "Point", "coordinates": [40.549, 38.5291]}}]}