{"type": "FeatureCollection", "id": "https://www.geonames.org/1425376", "name": "1425376", "features": [{"type": "Feature", "id": "http://data.archaeology.link/data/cigs/BST", "name": "Qa`la Bast", "dateprops": [], "properties": {"http://purl.org/dc/elements/1.1/created": ["2021"], "http://www.ancientports.com/ont#accuracy": ["3"], "http://www.opengis.net/ont/geosparql#hasGeometry": ["http://data.archaeology.link/data/cigs/BST_geom"], "http://www.w3.org/1999/02/22-rdf-syntax-ns#type": ["http://www.ancientports.com/ont#CuneiformSite"], "http://www.w3.org/2000/01/rdf-schema#label": ["", "Qa`la Bast"], "http://www.w3.org/2002/07/owl#sameAs": ["http://entitydata.org/entity/Q20182301"], "http://www.wikidata.org/prop/direct/P1566": ["https://www.geonames.org/1425376"]}, "geometry": {"type": "Point", "coordinates": [64.3566, 31.5081]}}]}